superpro/__init__.py
superpro/superpro.py
superpro-0.1.dist-info/LICENSE
superpro-0.1.dist-info/METADATA
superpro-0.1.dist-info/WHEEL
superpro-0.1.dist-info/top_level.txt
superpro-0.1.dist-info/RECORD
