Metadata-Version: 2.1
Name: superpro
Version: 0.1
Summary: tools
Home-page: https://github.com/javatechy/dokr
Author: Stefan Volk
Author-email: pliable.bride_0o@icloud.com
Classifier: Programming Language :: Python :: 3
Classifier: License :: OSI Approved :: MIT License
Classifier: Operating System :: OS Independent
License-File: LICENSE
